mm_base3/__init__.py
mm_base3/base_core.py
mm_base3/base_db.py
mm_base3/base_service.py
mm_base3/config.py
mm_base3/dconfig.py
mm_base3/dvalue.py
mm_base3/errors.py
mm_base3/py.typed
mm_base3/system_service.py
mm_base3/types_.py
mm_base3/utils.py
mm_base3/server/__init__.py
mm_base3/server/auth.py
mm_base3/server/jinja.py
mm_base3/server/server.py
mm_base3/server/utils.py
mm_base3/server/assets/base3.css
mm_base3/server/assets/base3.js
mm_base3/server/assets/pico.slate.min.css
mm_base3/server/assets/sortable.min.js
mm_base3/server/routers/__init__.py
mm_base3/server/routers/api_method_router.py
mm_base3/server/routers/auth_router.py
mm_base3/server/routers/system_router.py
mm_base3/server/templates/dconfig.j2
mm_base3/server/templates/dconfig_multiline.j2
mm_base3/server/templates/dconfig_toml.j2
mm_base3/server/templates/dlogs.j2
mm_base3/server/templates/dvalue.j2
mm_base3/server/templates/dvalue_update_field.j2
mm_base3/server/templates/login.j2
mm_base3/server/templates/system.j2
mm_base3/server/templates/inc/base.j2
mm_base3-0.0.13.dist-info/METADATA
mm_base3-0.0.13.dist-info/WHEEL
mm_base3-0.0.13.dist-info/RECORD
