Metadata-Version: 2.4
Name: mm-base3
Version: 0.0.13
Requires-Python: >=3.12
Requires-Dist: litestar[standard]>=2.15.1
Requires-Dist: mm-jinja==0.0.3
Requires-Dist: mm-mongo>=0.2.4
Requires-Dist: pydantic-settings>=2.8.0
